tensorflow_examples/__init__.py
tensorflow_examples/lite/__init__.py
tensorflow_examples/lite/model_maker/__init__.py
tensorflow_examples/lite/model_maker/cli/__init__.py
tensorflow_examples/lite/model_maker/cli/cli.py
tensorflow_examples/lite/model_maker/core/__init__.py
tensorflow_examples/lite/model_maker/core/compat.py
tensorflow_examples/lite/model_maker/core/export_format.py
tensorflow_examples/lite/model_maker/core/file_util.py
tensorflow_examples/lite/model_maker/core/test_util.py
tensorflow_examples/lite/model_maker/core/api/__init__.py
tensorflow_examples/lite/model_maker/core/api/api_gen.py
tensorflow_examples/lite/model_maker/core/api/api_util.py
tensorflow_examples/lite/model_maker/core/api/deprecated_api.py
tensorflow_examples/lite/model_maker/core/api/golden_api.json
tensorflow_examples/lite/model_maker/core/api/golden_api_doc.py
tensorflow_examples/lite/model_maker/core/api/include.py
tensorflow_examples/lite/model_maker/core/data_util/__init__.py
tensorflow_examples/lite/model_maker/core/data_util/audio_dataloader.py
tensorflow_examples/lite/model_maker/core/data_util/data_util.py
tensorflow_examples/lite/model_maker/core/data_util/dataloader.py
tensorflow_examples/lite/model_maker/core/data_util/image_dataloader.py
tensorflow_examples/lite/model_maker/core/data_util/image_searcher_dataloader.py
tensorflow_examples/lite/model_maker/core/data_util/metadata_loader.py
tensorflow_examples/lite/model_maker/core/data_util/object_detector_dataloader.py
tensorflow_examples/lite/model_maker/core/data_util/object_detector_dataloader_util.py
tensorflow_examples/lite/model_maker/core/data_util/recommendation_config.py
tensorflow_examples/lite/model_maker/core/data_util/recommendation_dataloader.py
tensorflow_examples/lite/model_maker/core/data_util/recommendation_testutil.py
tensorflow_examples/lite/model_maker/core/data_util/searcher_dataloader.py
tensorflow_examples/lite/model_maker/core/data_util/text_dataloader.py
tflite_model_maker_nightly-0.4.4.dev202402230613.dist-info/METADATA
tflite_model_maker_nightly-0.4.4.dev202402230613.dist-info/WHEEL
tflite_model_maker_nightly-0.4.4.dev202402230613.dist-info/entry_points.txt
tflite_model_maker_nightly-0.4.4.dev202402230613.dist-info/top_level.txt
tflite_model_maker_nightly-0.4.4.dev202402230613.dist-info/RECORD
